<?xml version="1.0"?>
<university name="&#x41C;&#x418;&#x424;&#x418;" city="&#x41C;&#x43E;&#x441;&#x43A;&#x432;&#x430;" metro="&#x41A;&#x430;&#x448;&#x438;&#x440;&#x441;&#x43A;&#x430;&#x44F;"><faculty name="&#x41A;&#x438;&#x411;" dean="&#x415;&#x432;&#x441;&#x435;&#x435;&#x432;"><department tag="K" name="&#x418;&#x43D;&#x444;&#x43E;&#x440;&#x43C;&#x430;&#x446;&#x438;&#x43E;&#x43D;&#x43D;&#x44B;&#x435; &#x441;&#x438;&#x441;&#x442;&#x435;&#x43C;&#x44B; &#x438; &#x442;&#x435;&#x445;&#x43D;&#x43E;&#x43B;&#x43E;&#x433;&#x438;&#x438;" number="36"><group name="&#x41A;5-361" number="1" amount="13" date="2012" fullname="K5-361"><student>Анисимова</student><student>Артемьев</student><student>Бубенко</student><student>Джелоухова</student><student>Заманов</student><student>Михеев</student><student>Пивоваров</student><student>Самсонов</student><student>Сидорова</student><student>Соловьёва</student><student>Тармазаков</student><student>Титоренко</student><student>Штанько</student></group><group name="&#x41A;5-362" number="2" amount="17" date="2012" fullname="K5-362"><student>Ахметсафин</student><student>Галкин</student><student>Головко</student><student>Джумайло</student><student>Ерохин</student><student>Каталкина</student><student>Левин</student><student>Молочков</student><student>Моряшова</student><student>Полстянкин</student><student>Пурик</student><student>Разживин</student><student>Редюк</student><student>Рябов</student><student>Скок</student><student>Стрекалов</student><student>Чайковская</student></group></department><department tag="K" name="&#x41F;&#x440;&#x43E;&#x433;&#x440;&#x430;&#x43C;&#x43C;&#x43D;&#x430;&#x44F; &#x438;&#x43D;&#x436;&#x435;&#x43D;&#x435;&#x440;&#x438;&#x44F;" number="22"><group name="&#x41A;5-221" number="1" amount="1" date="2012" fullname="K5-221"><student>Седова</student></group></department><department tag="K" name="&#x41C;&#x430;&#x442;&#x435;&#x43C;&#x430;&#x442;&#x438;&#x447;&#x435;&#x441;&#x43A;&#x43E;&#x435; &#x43E;&#x431;&#x435;&#x441;&#x43F;&#x435;&#x447;&#x435;&#x43D;&#x438;&#x435; &#x441;&#x438;&#x441;&#x442;&#x435;&#x43C;" number="33"><group name="&#x41A;5-331" number="1" amount="1" date="2012" fullname="K5-331"><student>Хузин</student></group></department><department tag="K" name="&#x418;&#x43D;&#x444;&#x43E;&#x440;&#x43C;&#x430;&#x446;&#x438;&#x43E;&#x43D;&#x43D;&#x44B;&#x435; &#x442;&#x435;&#x445;&#x43D;&#x43E;&#x43B;&#x43E;&#x433;&#x438;&#x438; &#x432; &#x441;&#x43E;&#x446;&#x438;&#x430;&#x43B;&#x44C;&#x43D;&#x44B;&#x445; &#x441;&#x438;&#x441;&#x442;&#x435;&#x43C;&#x430;&#x445;" number="68"><group name="&#x41A;5-682" number="2" amount="1" date="2012" fullname="K5-682"><student>Маляр</student></group></department></faculty><faculty name="&#x422;"><department tag="&#x422;" name="&#x41A;&#x430;&#x444;&#x435;&#x434;&#x440;&#x430; &#x43C;&#x43E;&#x43B;&#x435;&#x43A;&#x443;&#x43B;&#x44F;&#x440;&#x43D;&#x43E;&#x439; &#x444;&#x438;&#x437;&#x438;&#x43A;&#x438;" number="10"><group name="&#x422;3-101" number="1" amount="2" date="2013" fullname="&#x422;3-101"><student>Иванов</student><student>Петров</student><student>Сидоров</student></group></department></faculty></university>
